geckodriver_wrapper/__init__.py
geckodriver_wrapper/geckodriver.exe
geckodriver_wrapper-0.3.dist-info/LICENCE
geckodriver_wrapper-0.3.dist-info/METADATA
geckodriver_wrapper-0.3.dist-info/WHEEL
geckodriver_wrapper-0.3.dist-info/top_level.txt
geckodriver_wrapper-0.3.dist-info/RECORD
