Metadata-Version: 2.2
Name: geckodriver-wrapper
Version: 0.3
Summary: A packaged version of geckodriver for offline use.
Classifier: Programming Language :: Python :: 3
Classifier: License :: OSI Approved :: MIT License
Classifier: Operating System :: Microsoft :: Windows
License-File: LICENCE
Dynamic: classifier
Dynamic: summary
